streamtabs/__init__.py
streamtabs/core/__init__.py
streamtabs/core/core.py
streamtabs/core/sidebar.py
streamtabs-0.1.0.dist-info/METADATA
streamtabs-0.1.0.dist-info/WHEEL
streamtabs-0.1.0.dist-info/RECORD
