Metadata-Version: 2.3
Name: streamtabs
Version: 0.1.0
Summary: Streamlit Apps on Tabs
License: MIT
Author: Vishal Mishra
Author-email: vishal.k.mishra2@gmail.com
Requires-Python: >=3.10
Classifier: License :: OSI Approved :: MIT License
Classifier: Programming Language :: Python :: 3
Classifier: Programming Language :: Python :: 3.10
Classifier: Programming Language :: Python :: 3.11
Classifier: Programming Language :: Python :: 3.12
Classifier: Programming Language :: Python :: 3.13
Requires-Dist: streamlit (>=1.49.1,<2.0.0)
